peakselsdk/AccessLevel.py
peakselsdk/Account.py
peakselsdk/HttpClient.py
peakselsdk/Peaksel.py
peakselsdk/__init__.py
peakselsdk/batch/BatchClient.py
peakselsdk/batch/__init__.py
peakselsdk/blob/BinaryProtocol.py
peakselsdk/blob/BlobClient.py
peakselsdk/blob/Floats2d.py
peakselsdk/blob/Spectrum.py
peakselsdk/blob/__init__.py
peakselsdk/blob/blobs.py
peakselsdk/chromatogram/Chrom.py
peakselsdk/chromatogram/ChromClient.py
peakselsdk/chromatogram/__init__.py
peakselsdk/chromatogram/peak/Peak.py
peakselsdk/chromatogram/peak/PeakClient.py
peakselsdk/chromatogram/peak/__init__.py
peakselsdk/dr/DetectorRun.py
peakselsdk/dr/__init__.py
peakselsdk/injection/Injection.py
peakselsdk/injection/InjectionClient.py
peakselsdk/injection/__init__.py
peakselsdk/integrations/__init__.py
peakselsdk/integrations/matchms.py
peakselsdk/integrations/mocca.py
peakselsdk/org/Org.py
peakselsdk/org/OrgClient.py
peakselsdk/org/__init__.py
peakselsdk/plate/Plate.py
peakselsdk/plate/__init__.py
peakselsdk/signal/Floats.py
peakselsdk/signal/Range.py
peakselsdk/signal/__init__.py
peakselsdk/substance/Substance.py
peakselsdk/substance/SubstanceClient.py
peakselsdk/substance/__init__.py
peakselsdk/user/User.py
peakselsdk/user/__init__.py
peakselsdk/util/__init__.py
peakselsdk/util/api_util.py
peakselsdk/util/dict_util.py
elsci_peaksel_sdk-1.6.0.dist-info/METADATA
elsci_peaksel_sdk-1.6.0.dist-info/WHEEL
elsci_peaksel_sdk-1.6.0.dist-info/top_level.txt
elsci_peaksel_sdk-1.6.0.dist-info/RECORD
