Metadata-Version: 2.4
Name: elsci-peaksel-sdk
Version: 1.6.0
Summary: SDK to upload and manage chromatographic injections and other data in Elsci Peaksel
License: MIT License
Project-URL: Homepage, https://github.com/elsci-io/peaksel-sdk
Project-URL: Issues, https://github.com/elsci-io/peaksel-sdk/issues
Classifier: Programming Language :: Python :: 3
Classifier: License :: OSI Approved :: MIT License
Classifier: Operating System :: OS Independent
Requires-Python: >=3.11
Requires-Dist: urllib3>=2.6.3
